usgs_product_finder/__init__.py
usgs_product_finder/usgs_product_finder.py
usgs_product_finder/files/WRS2_descending.geojson
usgs_product_finder-0.0.5.dist-info/METADATA
usgs_product_finder-0.0.5.dist-info/WHEEL
usgs_product_finder-0.0.5.dist-info/top_level.txt
usgs_product_finder-0.0.5.dist-info/RECORD
