Metadata-Version: 2.1
Name: usgs-product-finder
Version: 0.0.5
Summary: USGS Finder Utility that finds USGS datasets based on a user input
Author: Ivica Matic
Author-email: <ivica.matic@spatialdays.com>
Keywords: usgs,landsat,satellite
Classifier: Development Status :: 1 - Planning
Classifier: Intended Audience :: Developers
Classifier: Programming Language :: Python :: 3
Classifier: Operating System :: Unix
Requires-Dist: requests ==2.31.0
Requires-Dist: shapely ==2.0.2
Requires-Dist: pandas ==2.1.1
Requires-Dist: geopandas ==0.14.0
